chartbook/__about__.py
chartbook/__init__.py
chartbook/build_docs.py
chartbook/cli.py
chartbook/create_data_glimpses.py
chartbook/data.py
chartbook/diagnostics.py
chartbook/errors.py
chartbook/manifest.py
chartbook/markdown_generator.py
chartbook/publish.py
chartbook/settings.py
chartbook/utils.py
chartbook/validation.py
chartbook/assets/android-chrome-192x192.png
chartbook/assets/android-chrome-512x512.png
chartbook/assets/apple-touch-icon.png
chartbook/assets/favicon-16x16.png
chartbook/assets/favicon-32x32.png
chartbook/assets/favicon.ico
chartbook/assets/logo.png
chartbook/assets/logo_only.png
chartbook/assets/site.webmanifest
chartbook/assets/wordmark_and_logo.png
chartbook/docs_src_catalog/charts.md
chartbook/docs_src_catalog/conf.py.j2
chartbook/docs_src_catalog/contributing.md
chartbook/docs_src_catalog/dataframes.md
chartbook/docs_src_catalog/diagnostics.md
chartbook/docs_src_catalog/index.md
chartbook/docs_src_catalog/pipelines.md
chartbook/docs_src_catalog/_static/chartbook-custom.js
chartbook/docs_src_catalog/_static/custom.css
chartbook/docs_src_catalog/_templates/blog_top_nav.html
chartbook/docs_src_catalog/_templates/chart_entry_bottom.md
chartbook/docs_src_catalog/_templates/chart_entry_top.md
chartbook/docs_src_catalog/_templates/dataframe_entry_top.md
chartbook/docs_src_catalog/_templates/dataframe_manifest.md
chartbook/docs_src_catalog/_templates/layout.html
chartbook/docs_src_catalog/_templates/pipeline_manifest.md
chartbook/docs_src_pipeline/charts.md
chartbook/docs_src_pipeline/conf.py.j2
chartbook/docs_src_pipeline/index.md
chartbook/docs_src_pipeline/_static/custom.css
chartbook/docs_src_pipeline/_templates/chart_entry_bottom.md
chartbook/docs_src_pipeline/_templates/chart_entry_top.md
chartbook/docs_src_pipeline/_templates/dataframe_entry_top.md
chartbook/docs_src_pipeline/_templates/dataframe_manifest.md
chartbook/docs_src_pipeline/_templates/pipeline_manifest.md
chartbook/plotting/__init__.py
chartbook/plotting/_api.py
chartbook-0.0.2.dist-info/METADATA
chartbook-0.0.2.dist-info/WHEEL
chartbook-0.0.2.dist-info/entry_points.txt
chartbook-0.0.2.dist-info/licenses/LICENSE.md
chartbook-0.0.2.dist-info/RECORD
